inverselap/__init__.py.py
inverselap/inverse.py
inverselap-1.3.2.dist-info/METADATA
inverselap-1.3.2.dist-info/WHEEL
inverselap-1.3.2.dist-info/license.txt
inverselap-1.3.2.dist-info/top_level.txt
inverselap-1.3.2.dist-info/RECORD
