Metadata-Version: 2.1
Name: inverselap
Version: 1.3.2
Summary: Provides a variety of numerical inversion methods for the inverse Laplace transform
Home-page: UNKNOWN
Author: renger
License: UNKNOWN
Platform: UNKNOWN
Requires-Dist: mpmath (>=1.2.1)
Requires-Dist: numpy (>=1.19.3)
Requires-Dist: scipy (>=1.5.4)
